TittaPy_v1.cpython-313-x86_64-linux-gnu.so
TittaPy_v2.cpython-313-x86_64-linux-gnu.so
tittapy.libs/libavahi-client-373b7738.so.3.2.9
tittapy.libs/libavahi-common-91518825.so.3.5.4
tittapy.libs/libcap-6500f43e.so.2.48
tittapy.libs/libdbus-1-43555f95.so.3.19.13
tittapy.libs/libgcrypt-3098dcde.so.20.4.0
tittapy.libs/libgpg-error-df6ee685.so.0.32.0
tittapy.libs/liblz4-9ba322f5.so.1.9.3
tittapy.libs/liblzma-270e41f3.so.5.2.5
tittapy.libs/libsystemd-c5cae820.so.0.35.0
tittapy.libs/libtobii_research-37413a8c.so.2
tittapy.libs/libtobii_research-a85796b1.so.1
tittapy.libs/libzstd-82d8f7e0.so.1.5.5
tittapy-2.0.0.dist-info/METADATA
tittapy-2.0.0.dist-info/WHEEL
tittapy-2.0.0.dist-info/top_level.txt
tittapy-2.0.0.dist-info/RECORD
