Metadata-Version: 2.1
Name: TittaPy
Version: 2.0.0
Summary: Interface to Tobii eye trackers using Tobii Pro SDK
Home-page: https://github.com/dcnieho/Titta
Author: Diederick C. Niehorster
Author-email: diederick_c.niehorster@humlab.lu.se
Keywords: Tobii PsychoPy Eye-tracking
Classifier: Development Status :: 5 - Production/Stable
Classifier: Intended Audience :: Science/Research
Classifier: Topic :: Scientific/Engineering
Classifier: Topic :: Software Development :: Libraries
Classifier: Environment :: MacOS X
Classifier: Environment :: Win32 (MS Windows)
Classifier: Environment :: X11 Applications
Classifier: Operating System :: Microsoft :: Windows
Classifier: Operating System :: MacOS :: MacOS X
Classifier: Operating System :: POSIX :: Linux
Classifier: Programming Language :: Python :: 3
Classifier: Programming Language :: C++
Requires-Python: >=3.8
Requires-Dist: numpy
